thedonald/__init__.py
thedonald/__main__.py
thedonald/auth.py
thedonald/generate.py
thedonald/tweets.py
thedonald-1.0.4.dist-info/DESCRIPTION.rst
thedonald-1.0.4.dist-info/METADATA
thedonald-1.0.4.dist-info/RECORD
thedonald-1.0.4.dist-info/WHEEL
thedonald-1.0.4.dist-info/metadata.json
thedonald-1.0.4.dist-info/top_level.txt
