Metadata-Version: 2.0
Name: thedonald
Version: 1.0.4
Summary: A Markov text generator generating fake Trump quotes from Trump's tweets.
Home-page: http://luke.deentaylor.com/
Author: Luke Taylor
Author-email: luke@deentaylor.com
License: UNKNOWN
Platform: UNKNOWN
Requires-Dist: tweepy
